lavaplay/__init__.py
lavaplay/client.py
lavaplay/emitter.py
lavaplay/events.py
lavaplay/exceptions.py
lavaplay/node_manager.py
lavaplay/objects.py
lavaplay/player.py
lavaplay/rest.py
lavaplay/routes.py
lavaplay/utlits.py
lavaplay/ws.py
lavaplay_py-1.0.18a0.dist-info/licenses/LICENSE
lavaplay_py-1.0.18a0.dist-info/METADATA
lavaplay_py-1.0.18a0.dist-info/WHEEL
lavaplay_py-1.0.18a0.dist-info/top_level.txt
lavaplay_py-1.0.18a0.dist-info/RECORD
