Metadata-Version: 2.4
Name: lavaplay.py
Version: 1.0.18a0
Summary: Its a lavalink nodes manger to make a music bots for discord with python.
Home-page: https://github.com/HazemMeqdad/lavaplay.py
Author: HazemMeqdad
Author-email: hazemmeqdad@outlook.com
Project-URL: Bug Reports, https://github.com/HazemMeqdad/lavaplay.py/issues
Project-URL: Source, https://github.com/HazemMeqdad/lavaplay.py/
Project-URL: Documentation, https://lavaplay.readthedocs.io/en/latest
Keywords: lavalink,discord,discord-lavalink,lavaplay,lavaplay.py
Classifier: Development Status :: 5 - Production/Stable
Classifier: Intended Audience :: Developers
Classifier: Topic :: Software Development :: Build Tools
Classifier: License :: OSI Approved :: MIT License
Classifier: Programming Language :: Python :: 3
Classifier: Programming Language :: Python :: 3.8
Classifier: Programming Language :: Python :: 3.9
Classifier: Programming Language :: Python :: 3.10
Classifier: Programming Language :: Python :: 3.11
Classifier: Programming Language :: Python :: 3.12
Classifier: Programming Language :: Python :: 3 :: Only
License-File: LICENSE
Requires-Dist: aiohttp
Dynamic: author
Dynamic: author-email
Dynamic: classifier
Dynamic: description
Dynamic: description-content-type
Dynamic: home-page
Dynamic: keywords
Dynamic: license-file
Dynamic: project-url
Dynamic: requires-dist
Dynamic: summary
